cdk_ecs_service_extensions/__init__.py
cdk_ecs_service_extensions/py.typed
cdk_ecs_service_extensions/_jsii/__init__.py
cdk_ecs_service_extensions/_jsii/ecs-service-extensions@2.0.0.jsii.tgz
cdk_ecs_service_extensions-2.0.0.dist-info/LICENSE
cdk_ecs_service_extensions-2.0.0.dist-info/METADATA
cdk_ecs_service_extensions-2.0.0.dist-info/NOTICE
cdk_ecs_service_extensions-2.0.0.dist-info/WHEEL
cdk_ecs_service_extensions-2.0.0.dist-info/top_level.txt
cdk_ecs_service_extensions-2.0.0.dist-info/RECORD
